arduinodisco/__init__.py
arduinodisco/arduino_db.py
arduinodisco/discovery.py
arduinodisco/main.py
arduinodisco/paths.py
arduinodisco/ports.py
arduino_disco-0.1.0.dist-info/METADATA
arduino_disco-0.1.0.dist-info/WHEEL
arduino_disco-0.1.0.dist-info/entry_points.txt
arduino_disco-0.1.0.dist-info/top_level.txt
arduino_disco-0.1.0.dist-info/RECORD
