Metadata-Version: 2.4
Name: arduino-disco
Version: 0.1.0
Summary: A library to discover Arduino boards connected via serial ports
Author-email: Christoph Schueler <cou12.gems@googlemail.com>
License: MIT
Project-URL: Homepage, https://github.com/christoph2/arduino-disco
Keywords: arduino,serial,discovery,embedded
Classifier: Programming Language :: Python :: 3
Classifier: License :: OSI Approved :: MIT License
Classifier: Operating System :: OS Independent
Requires-Python: >=3.7
Requires-Dist: pyserial
Provides-Extra: dev
Requires-Dist: bumpver; extra == "dev"
Requires-Dist: pre-commit; extra == "dev"
